CONTRIBUTING.md
CONTRIBUTORS.md
LICENSE.txt
MANIFEST.in
README.md
setup.cfg
setup.py
tox.ini
version.txt
helium/__about__.py
helium/__init__.py
helium/_version.py
helium/client.py
helium/configuration.py
helium/device.py
helium/device_configuration.py
helium/element.py
helium/exceptions.py
helium/label.py
helium/metadata.py
helium/organization.py
helium/relations.py
helium/resource.py
helium/sensor.py
helium/session.py
helium/timeseries.py
helium/user.py
helium/util.py
helium/adapter/__init__.py
helium/adapter/aiohttp.py
helium/adapter/requests.py
helium_python.egg-info/PKG-INFO
helium_python.egg-info/SOURCES.txt
helium_python.egg-info/dependency_links.txt
helium_python.egg-info/requires.txt
helium_python.egg-info/top_level.txt