Metadata-Version: 1.0
Name: helium-python
Version: 0.6.0
Summary: Wrapper for the Helium API
Home-page: https://github.com/helium/helium-python
Author: Helium
Author-email: hello@helium.com
License: BSD
Platform: UNKNOWN
